depalma_napari_omero/__init__.py
depalma_napari_omero/__main__.py
depalma_napari_omero/_version.py
depalma_napari_omero/cli.py
depalma_napari_omero/napari.yaml
depalma_napari_omero/omero_client/__init__.py
depalma_napari_omero/omero_client/_client.py
depalma_napari_omero/omero_client/_compute.py
depalma_napari_omero/omero_client/_context.py
depalma_napari_omero/omero_client/_project.py
depalma_napari_omero/omero_client/_scanner.py
depalma_napari_omero/omero_client/_tags_processor.py
depalma_napari_omero/omero_client/_utils.py
depalma_napari_omero/omero_client/_view.py
depalma_napari_omero/omero_client/omero_config.py
depalma_napari_omero/widgets/__init__.py
depalma_napari_omero/widgets/_widget.py
depalma_napari_omero/widgets/_worker.py
depalma_napari_omero-0.4.3.dist-info/licenses/LICENSE
depalma_napari_omero-0.4.3.dist-info/METADATA
depalma_napari_omero-0.4.3.dist-info/WHEEL
depalma_napari_omero-0.4.3.dist-info/entry_points.txt
depalma_napari_omero-0.4.3.dist-info/top_level.txt
depalma_napari_omero-0.4.3.dist-info/RECORD
