Metadata-Version: 2.4
Name: depalma-napari-omero
Version: 0.4.3
Summary: Napari interface for the De Palma lab.
Author-email: Mallory Wittwer <mallory.wittwer@epfl.ch>
License:                     GNU AFFERO GENERAL PUBLIC LICENSE
Project-URL: homepage, https://github.com/EPFL-Center-for-Imaging/depalma-napari-omero
Project-URL: repository, https://github.com/EPFL-Center-for-Imaging/depalma-napari-omero
Classifier: Development Status :: 2 - Pre-Alpha
Classifier: License :: OSI Approved :: BSD License
Classifier: Programming Language :: Python :: 3
Classifier: Programming Language :: Python :: 3.10
Classifier: Topic :: Scientific/Engineering :: Image Processing
Requires-Python: <3.11,>=3.10
License-File: LICENSE
Requires-Dist: ezomero
Requires-Dist: numpy
Requires-Dist: pandas
Requires-Dist: tifffile
Requires-Dist: pooch
Requires-Dist: questionary
Requires-Dist: aicsimageio
Requires-Dist: napari[all]
Requires-Dist: napari-toolkit
Requires-Dist: napari-adaptive-painting
Requires-Dist: imaging-server-kit>=0.1.3
Requires-Dist: mousetumorpy>=0.0.4
Requires-Dist: napari-mousetumorpy>=0.0.3
Dynamic: license-file
